hother/__init__.py
hother/streamblocks/__init__.py
hother/streamblocks/adapters/__init__.py
hother/streamblocks/adapters/categories.py
hother/streamblocks/adapters/detection.py
hother/streamblocks/adapters/protocols.py
hother/streamblocks/adapters/input/__init__.py
hother/streamblocks/adapters/input/identity.py
hother/streamblocks/adapters/output/__init__.py
hother/streamblocks/adapters/output/streamblocks.py
hother/streamblocks/core/__init__.py
hother/streamblocks/core/_logger.py
hother/streamblocks/core/block_state_machine.py
hother/streamblocks/core/constants.py
hother/streamblocks/core/line_accumulator.py
hother/streamblocks/core/models.py
hother/streamblocks/core/parsing.py
hother/streamblocks/core/processor.py
hother/streamblocks/core/protocol_processor.py
hother/streamblocks/core/registry.py
hother/streamblocks/core/types.py
hother/streamblocks/core/utils.py
hother/streamblocks/extensions/__init__.py
hother/streamblocks/extensions/agui/__init__.py
hother/streamblocks/extensions/agui/filters.py
hother/streamblocks/extensions/agui/input_adapter.py
hother/streamblocks/extensions/agui/output_adapter.py
hother/streamblocks/extensions/anthropic/__init__.py
hother/streamblocks/extensions/gemini/__init__.py
hother/streamblocks/extensions/openai/__init__.py
hother/streamblocks/integrations/__init__.py
hother/streamblocks/integrations/pydantic_ai/README.md
hother/streamblocks/integrations/pydantic_ai/__init__.py
hother/streamblocks/integrations/pydantic_ai/agent.py
hother/streamblocks/integrations/pydantic_ai/processor.py
hother/streamblocks/syntaxes/__init__.py
hother/streamblocks/syntaxes/base.py
hother/streamblocks/syntaxes/delimiter.py
hother/streamblocks/syntaxes/factory.py
hother/streamblocks/syntaxes/markdown.py
hother/streamblocks/syntaxes/models.py
hother/streamblocks_examples/README.md
hother/streamblocks_examples/__init__.py
hother/streamblocks_examples/pyproject.toml
hother/streamblocks_examples/run_examples.py
streamblocks-0.3.6.dist-info/METADATA
streamblocks-0.3.6.dist-info/WHEEL
streamblocks-0.3.6.dist-info/licenses/LICENSE
streamblocks-0.3.6.dist-info/RECORD
