Metadata-Version: 2.4
Name: streamblocks
Version: 0.3.6
Summary: Real-time extraction and processing of structured blocks from text streams
Project-URL: Homepage, https://github.com/streamblocks/streamblocks
Project-URL: Bug Tracker, https://github.com/streamblocks/streamblocks/issues
Project-URL: Source, https://github.com/streamblocks/streamblocks
Project-URL: Documentation, https://streamblocks.github.io/streamblocks/latest/
License-File: LICENSE
Classifier: Development Status :: 3 - Alpha
Classifier: License :: OSI Approved :: MIT License
Classifier: Operating System :: OS Independent
Classifier: Programming Language :: Python :: 3
Classifier: Programming Language :: Python :: 3.13
Classifier: Topic :: Software Development :: Libraries :: Python Modules
Classifier: Topic :: Text Processing
Classifier: Typing :: Typed
Requires-Python: >=3.13
Requires-Dist: pydantic-ai>=1.0.9
Requires-Dist: pydantic>=2.12.4
Requires-Dist: pyyaml>=6.0
Requires-Dist: textual>=6.1.0
Provides-Extra: all-providers
Requires-Dist: anthropic>=0.18.0; extra == 'all-providers'
Requires-Dist: google-genai>=1.38.0; extra == 'all-providers'
Requires-Dist: openai>=1.0.0; extra == 'all-providers'
Provides-Extra: anthropic
Requires-Dist: anthropic>=0.18.0; extra == 'anthropic'
Provides-Extra: examples
Requires-Dist: hother-cancelable>=0.1.0; extra == 'examples'
Requires-Dist: streamblocks-examples; extra == 'examples'
Provides-Extra: gemini
Requires-Dist: google-genai>=1.38.0; extra == 'gemini'
Provides-Extra: loguru
Requires-Dist: loguru>=0.7.0; extra == 'loguru'
Provides-Extra: openai
Requires-Dist: openai>=1.0.0; extra == 'openai'
Provides-Extra: structlog
Requires-Dist: structlog>=24.1.0; extra == 'structlog'
